{"sections":{"2feb3b2b-6c6e-44ce-b1f3-bcfe304be116":{"type":"text--rich-text","custom_css":[".rte {text-align: left;}","h3 {text-align: center;}"],"settings":{"colors":"white","title":"Refund policy","text":"<p>There will be no returns or refunds for any sales made. However, if a genetic disease is detected within 12 months of purchase, you may return the cat and receive a complete refund in accordance with our Terms & Conditions contract. Please refer to our Terms & Conditions for further details.<\/p><p>If you have any queries, kindly reach out to us here.<\/p>","button_label":"","button_link":""}},"custom-html-00":{"type":"advanced-layout--custom-html","settings":{}},"custom-html-01":{"type":"advanced-layout--custom-html","settings":{}},"custom-html-02":{"type":"advanced-layout--custom-html","settings":{}},"custom-html-03":{"type":"advanced-layout--custom-html","blocks":{"1648804512a39eca6c-0":{"type":"html","settings":{"code":"<div style=\"text-align:center; padding: 16px 0;\"><\/div>","width":"100%"}}},"block_order":["1648804512a39eca6c-0"],"settings":{}},"main":{"type":"template--page","disabled":true,"settings":{"page_title_enabled":true,"page_width":"full-width"}}},"order":["2feb3b2b-6c6e-44ce-b1f3-bcfe304be116","custom-html-00","custom-html-01","custom-html-02","custom-html-03","main"]}